<?xml version="1.0" encoding="utf-8" ?>
<dwsync>
<file name="generator_config.txt" server="C:/wamp64/www/" local="130745106280000000" remote="130745106280000000" Dst="0" />
<file name="rationale-regular-demo.html" server="C:/wamp64/www/" local="130745106280000000" remote="130745106280000000" Dst="0" />
<file name="rationale-regular-webfont.eot" server="C:/wamp64/www/" local="130745106280000000" remote="130745106280000000" Dst="0" />
<file name="rationale-regular-webfont.svg" server="C:/wamp64/www/" local="130745106280000000" remote="130745106280000000" Dst="0" />
<file name="rationale-regular-webfont.ttf" server="C:/wamp64/www/" local="130745106280000000" remote="130745106280000000" Dst="0" />
<file name="rationale-regular-webfont.woff" server="C:/wamp64/www/" local="130745106280000000" remote="130745106280000000" Dst="0" />
<file name="rationale-regular-webfont.woff2" server="C:/wamp64/www/" local="130745106280000000" remote="130745106280000000" Dst="0" />
<file name="stylesheet.css" server="C:/wamp64/www/" local="130745106280000000" remote="130745106280000000" Dst="0" />
<file name="webfontkit-20150426-043002.zip" server="C:/wamp64/www/" local="130745106280000000" remote="130745106280000000" Dst="0" />
</dwsync>