<?xml version="1.0" encoding="utf-8" ?>
<dwsync>
<file name="OO6PT80.jpg" server="D:/wamp64/www/" local="131362823840000000" remote="131362823840000000" Dst="0" />
<file name="pngaaa.com-119565.png" server="D:/wamp64/www/" local="132686884325712882" remote="132686884320000000" Dst="0" />
<file name="beyaz-renk.png" server="D:/wamp64/www/" local="132686955308197485" remote="132686955300000000" Dst="0" />
<file name="midsection-of-doctor-discussing-with-patient-at-table-in-clinic-888267910-4181894ed6b24b4cb644e6d144242da3.jpg" server="D:/wamp64/www/" local="132689216698502239" remote="132689216690000000" Dst="0" />
<file name="pexels-gustavo-fring-4173239.jpg" server="D:/wamp64/www/" local="132689271893089371" remote="132689271890000000" Dst="0" />
<file name="indir.png" server="D:/wamp64/www/" local="132689315301099375" remote="132689315300000000" Dst="0" />
<file name="clock.png" server="D:/wamp64/www/" local="132689337895900445" remote="132689337890000000" Dst="0" />
<file name="png-clipart-arturia-business-logo-musical-instruments-individual-retirement-account-logo-business.png" server="D:/wamp64/www/" local="132689340886875640" remote="132689340880000000" Dst="0" />
<file name="prof.jpg" server="D:/wamp64/www/" local="132689341749952713" remote="132689341740000000" Dst="0" />
<file name="prof.png" server="D:/wamp64/www/" local="132689343695560411" remote="132689343690000000" Dst="0" />
<file name="çıkış.png" server="D:/wamp64/www/" local="132689347000554899" remote="132689347000000000" Dst="0" />
<file name="çıkış1.png" server="D:/wamp64/www/" local="132689353925281012" remote="132689353920000000" Dst="0" />
<file name="anasayfa resim.png" server="D:/wamp64/www/" local="132689362913550470" remote="132689362910000000" Dst="0" />
<file name="blurlu.jpg" server="D:/wamp64/www/" local="132689550431333701" remote="132689550430000000" Dst="0" />
<file name="pexels-gustavo-fring-4173239.jpg" server="C:/wamp64/www/" local="132689271893089371" remote="132689271890000000" Dst="0" />
<file name="beyaz-renk.png" server="C:/wamp64/www/" local="132686955308197485" remote="132686955300000000" Dst="0" />
<file name="pngaaa.com-119565.png" server="C:/wamp64/www/" local="132686884325712882" remote="132686884320000000" Dst="0" />
<file name="indir.png" server="C:/wamp64/www/" local="132689315301099375" remote="132689315300000000" Dst="0" />
<file name="clock.png" server="C:/wamp64/www/" local="132689337895900445" remote="132689337890000000" Dst="0" />
<file name="prof.png" server="C:/wamp64/www/" local="132689343695560411" remote="132689343690000000" Dst="0" />
<file name="çıkış.png" server="C:/wamp64/www/" local="132689347000554899" remote="132689347000000000" Dst="0" />
<file name="çıkış1.png" server="C:/wamp64/www/" local="132689353925281012" remote="132689353920000000" Dst="0" />
<file name="prof.jpg" server="C:/wamp64/www/" local="132689341749952713" remote="132689341740000000" Dst="0" />
<file name="png-clipart-arturia-business-logo-musical-instruments-individual-retirement-account-logo-business.png" server="C:/wamp64/www/" local="132689340886875640" remote="132689340880000000" Dst="0" />
<file name="phpMyAdmin-5.1.1-all-languages.zip" server="C:/wamp64/www/" local="132690950116392067" remote="132690950110000000" Dst="0" />
<file name="OO6PT80.jpg" server="C:/wamp64/www/" local="131362823840000000" remote="131362823840000000" Dst="0" />
<file name="midsection-of-doctor-discussing-with-patient-at-table-in-clinic-888267910-4181894ed6b24b4cb644e6d144242da3.jpg" server="C:/wamp64/www/" local="132689216698502239" remote="132689216690000000" Dst="0" />
<file name="blurlu.jpg" server="C:/wamp64/www/" local="132689550431333701" remote="132689550430000000" Dst="0" />
<file name="anasayfa resim.png" server="C:/wamp64/www/" local="132689362913550470" remote="132689362910000000" Dst="0" />
</dwsync>